README.md
setup.cfg
setup.py
cbauth/__init__.py
cbauth/admin.py
cbauth/apps.py
cbauth/models.py
cbauth/serializers.py
cbauth/signals.py
cbauth/tests.py
cbauth/views.py
cbauth.egg-info/PKG-INFO
cbauth.egg-info/SOURCES.txt
cbauth.egg-info/dependency_links.txt
cbauth.egg-info/not-zip-safe
cbauth.egg-info/requires.txt
cbauth.egg-info/top_level.txt
cbauth/migrations/__init__.py
cbauth/urls/__init__.py
cbauth/urls/api.py
cbauth/urls/pages.py