Metadata-Version: 1.1
Name: cbauth
Version: 1.0.5
Summary: Django simplified version of authorization with template views and RESTFul API
Home-page: https://github.com/codebolab/auth
Author: code.bo
Author-email: info@code.bo
License: UNKNOWN
Platform: UNKNOWN
Classifier: Programming Language :: Python
